pvarc/__init__.py
pvarc/astmg173.csv
pvarc/color.py
pvarc/fit.py
pvarc/fit_old.py
pvarc/image.py
pvarc/main.py
pvarc/materials.py
pvarc/metrics.py
pvarc/oceaninsight.py
pvarc/tmm.py
pvarc/cameras/MVL23M23.csv
pvarc/cameras/Ximea-MC050cg_combined_labeled.csv
pvarc/sources/LEDW7E_A01_intensity.csv
pvarc-0.1.0.dist-info/LICENSE
pvarc-0.1.0.dist-info/METADATA
pvarc-0.1.0.dist-info/WHEEL
pvarc-0.1.0.dist-info/top_level.txt
pvarc-0.1.0.dist-info/RECORD
