Metadata-Version: 2.1
Name: pvarc
Version: 0.1.0
Summary: Analyze anti-reflection coatings on the air-glass interface of a photovoltaic module.
Home-page: https://github.com/DuraMAT/pvarc
Author: toddkarin
Author-email: pvtools.lbl@gmail.com
License: UNKNOWN
Platform: UNKNOWN
Classifier: Programming Language :: Python :: 3
Classifier: License :: OSI Approved :: MIT License
Classifier: Operating System :: OS Independent
Requires-Dist: numpy
Requires-Dist: pandas
Requires-Dist: scipy
Requires-Dist: matplotlib
Requires-Dist: tmm
Requires-Dist: colour-science
Requires-Dist: tqdm
